Workbook
Name Tabla_Maestra: 'Tabla Maestra '!$A$1:$V$5

Sheet tm
A1: año | B1: Metrica | C1: Valor(USD)
A2: 2023 | B2: Ingresos totales | C2: 31436023
A3: 2023 | B3: Costo de ventas | C3: 13042200
A4: 2023 | B4: Utilidad bruta | C4: 18393823
A5: 2023 | B5: EBITDA | C5: 11221761
A6: 2023 | B6: EBIT | C6: 6406528
A7: 2023 | B7: Utilidad Neta | C7: 1036253
A8: 2023 | B8: Patrimonio | C8: 32400000
A9: 2023 | B9: Activos Totales | C9: 146854080
A10: 2023 | B10: Deuda Total | C10: 114454000
A11: 2023 | B11: Gastos Financieros | C11: 10586995
A12: 2023 | B12: NOPAT | C12: 4804896
A13: 2023 | B13: Días Inventario | C13: 40
... A43: 2025 | B43: DíasCxP | C43: 25

Sheet Tabla Maestra 
A1: Tabla Maestra
A2: Año | B2: Ingresos totales | C2: Costo de ventas | D2: Utilidad bruta | E2: EBITDA | F2: EBIT | G2: Utilidad Neta | H2: Patrimonio | I2: Activos Totales | J2: Deuda Total | K2: Gastos Financieros | L2: NOPAT | M2: Días Inventario | N2: Días CxC | O2: DíasCxP
A3: 2023 | B3: 31436023 | C3: 13042200 | D3: =B3-C3 -> 18393823 | E3: 11221761 | F3: 6406528 | G3: 1036253 | H3: 32400000 | I3: 146854080 | J3: 114454000 | K3: =TablaMaestra[[#This Row],[Deuda Total]]*0.0925 -> 10586995 | L3: =TablaMaestra[ [#This Row],[ EBIT] ]*0.75 -> 4804896 | M3: 40 | N3: 55 | O3: 23
A4: 2024 | B4: =9677747*4 -> 38710988 | C4: =B4*(C3/B3) -> 16060443 | D4: =B4-C4 -> 22650545 | E4: =B4*(E3/B3) -> 13818715 | F4: 11200000 | G4: 1276064 | H4: 33499616 | I4: 148510831 | J4: 113354464 | K4: =TablaMaestra[[#This Row],[Deuda Total]]*0.0925 -> 10485288 | L4: =TablaMaestra[ [#This Row],[ EBIT] ]*0.75 -> 8400000 | M4: 38 | N4: 54 | O4: 24
A5: 2025 | B5: =B4*1.15 -> 44517636 | C5: 17801745 | D5: 26715892 | E5: 16559287 | F5: 13000000 | G5: 1912650 | H5: 29742068 | I5: 152543200 | J5: 122801110 | K5: =TablaMaestra[[#This Row],[Deuda Total]]*0.0925 -> 11359103 | L5: =TablaMaestra[ [#This Row],[ EBIT] ]*0.75 -> 9750000 | M5: 37 | N5: 53 | O5: 25

Sheet Ratios
A1: Año | B1: Activo Corriente | C1: Pasivo Corriente | D1: Pasivo No Corriente | E1: Total Activos | F1: Total Pasivos | G1: Patrimonio | H1: Razon circulante | I1: prueba acida | J1: D/E | K1: Deuda/Activos | L1: Capital de Trabajo | M1: Cobertura de intereses | N1: WACC | P1: Año | Q1: % Deuda | R1: % Patrimonio
A2: 2023 | B2: 37134132 | C2: 37489630 | D2: 35530538 | E2: 87635634 | F2: 73020168 | G2: 14615467 | H2: =B2/C2 -> 0.99051743 | I2: =B2*0.9 / C2 -> 0.89146569 | J2: =F2/G2 -> 4.9960886 | K2: =F2/E2 -> 0.83322462 | L2: =B2-C2 -> -355498 | M2: ='Tabla Maestra '!F3/'Tabla Maestra '!K3 -> 0.60513186 | N2: =0.11*(1/(1+J2))+0.0925*(1-0.25)*(J2/(1+J2)) -> 0.07615025 | P2: 2023 | Q2: =F2/(F2+G2) -> 0.83322461 | R2: =G2/(F2+G2) -> 0.16677539
A3: 2024 | B3: 50456351 | C3: 31477334 | D3: 54896554 | E3: 100109385 | F3: 86373888 | G3: 13735498 | H3: =B3/C3 -> 1.6029423 | I3: =B3*0.9 / C3 -> 1.4426481 | J3: =F3/G3 -> 6.2883696 | K3: =F3/E3 -> 0.86279511 | L3: =B3-C3 -> 18979017 | M3: ='Tabla Maestra '!F4/'Tabla Maestra '!K4 -> 1.0681633 | N3: =0.11*(1/(1+J3))+0.0925*(1-0.25)*(J3/(1+J3)) -> 0.074948949 | P3: 2024 | Q3: =F3/(F3+G3) -> 0.8627951 | R3: =G3/(F3+G3) -> 0.1372049
A4: 2025 Q2 | B4: 52000000 | C4: 38000000 | D4: 84801110 | E4: 152543200 | F4: 122801110 | G4: 29742068 | H4: =B4/C4 -> 1.3684211 | I4: =B4*0.9 / C4 -> 1.2315789 | J4: =F4/G4 -> 4.1288693 | K4: =F4/E4 -> 0.80502513 | L4: =B4-C4 -> 14000000 | M4: ='Tabla Maestra '!F5/'Tabla Maestra '!K5 -> 1.1444566 | N4: =0.11*(1/(1+J4))+0.0925*(1-0.25)*(J4/(1+J4)) -> 0.077295849 | P4: 2025 | Q4: =F4/(F4+G4) -> 0.80502525 | R4: =G4/(F4+G4) -> 0.19497475

Sheet Analisis Verical-Horizontal 
F1: Analisis vertical (%) | K1: Analisis Horizontal (Crecimiento Interanual)
A2: Metricas | B2: 2023 | C2: 2024 | D2: 2025 | F2: Métrica | G2: Fórmula 2023 | H2: Fórmula 2024 | I2: Fórmula 2025 | K2: Métrica | L2: 2023 | M2: 2024 | N2: 2025 | O2: Δ 24 vs 23 (USD) | P2: Δ 25 vs 24 (USD) | Q2: Var % 24 vs 23 | R2: Var % 25 vs 24
A3: Ingresos Totales | B3: ='Tabla Maestra '!B3 -> 31436023 | C3: ='Tabla Maestra '!B4 -> 38710988 | D3: ='Tabla Maestra '!B5 -> 44517636 | F3: Ingresos Totales | G3: =B3/B3 -> 1 | H3: =C3/C3 -> 1 | I3: =D4/D4 -> 1 | K3: Ingresos Totales | L3: =B3 -> 31436023 | M3: =C3 -> 38710988 | N3: =D3 -> 44517636 | O3: =C3-B3 -> 7274965 | P3: =D3-C3 -> 5806648.2 | Q3: =(C3-B3)/B3 -> 0.23142129 | R3: =(D3-C3)/C3 -> 0.15
A4: Costo de Ventas | B4: ='Tabla Maestra '!C3 -> 13042200 | C4: ='Tabla Maestra '!C4 -> 16060443 | D4: ='Tabla Maestra '!C5 -> 17801745 | F4: Costo de Ventas | G4: =B4/B3 -> 0.41488072 | H4: =C4/C3 -> 0.41488072 | I4: =D4/D3 -> 0.39988073 | K4: Costo de Ventas | L4: =B4 -> 13042200 | M4: =C4 -> 16060443 | N4: =D4 -> 17801745 | O4: =C4-B4 -> 3018242.8 | P4: =D4-C4 -> 1741302.2 | Q4: =(C4-B4)/B4 -> 0.23142129 | R4: =(D4-C4)/C4 -> 0.10842181
A5: Utilidad Bruta | B5: ='Tabla Maestra '!D3 -> 18393823 | C5: ='Tabla Maestra '!D4 -> 22650545 | D5: ='Tabla Maestra '!D5 -> 26715892 | F5: Utilidad Bruta | G5: =B5/B3 -> 0.58511928 | H5: =C5/C3 -> 0.58511928 | I5: =D5/D3 -> 0.60011928 | K5: Utilidad Bruta | L5: =B5 -> 18393823 | M5: =C5 -> 22650545 | N5: =D5 -> 26715892 | O5: =C5-B5 -> 4256722.2 | P5: =D5-C5 -> 4065346.8 | Q5: =(C5-B5)/B5 -> 0.23142129 | R5: =(D5-C5)/C5 -> 0.17948119
A6: EBITDA | B6: ='Tabla Maestra '!E3 -> 11221761 | C6: ='Tabla Maestra '!E4 -> 13818715 | D6: ='Tabla Maestra '!E5 -> 16559287 | F6: EBITDA | G6: =B6/B3 -> 0.3569714 | H6: =C6/C3 -> 0.3569714 | I6: =D6/D3 -> 0.37197139 | K6: EBITDA | L6: =B6 -> 11221761 | M6: =C6 -> 13818715 | N6: =D6 -> 16559287 | O6: =C6-B6 -> 2596954.4 | P6: =D6-C6 -> 2740571.6 | Q6: =(C6-B6)/B6 -> 0.23142129 | R6: =(D6-C6)/C6 -> 0.19832318
A7: EBIT | B7: ='Tabla Maestra '!F3 -> 6406528 | C7: ='Tabla Maestra '!F4 -> 11200000 | D7: ='Tabla Maestra '!F5 -> 13000000 | F7: EBIT | G7: =B7/B3 -> 0.20379575 | H7: =C7/C3 -> 0.28932354 | I7: =D7/D3 -> 0.2920191 | K7: EBIT | L7: =B7 -> 6406528 | M7: =C7 -> 11200000 | N7: =D7 -> 13000000 | O7: =C7-B7 -> 4793472 | P7: =D7-C7 -> 1800000 | Q7: =(C7-B7)/B7 -> 0.74821682 | R7: =(D7-C7)/C7 -> 0.16071429
A8: Utilidad Neta | B8: ='Tabla Maestra '!G3 -> 1036253 | C8: ='Tabla Maestra '!G4 -> 1276064 | D8: ='Tabla Maestra '!G5 -> 1912650 | F8: Utilidad Neta | G8: =B8/B3 -> 0.032963871 | H8: =C8/C3 -> 0.032963871 | I8: =D8/D3 -> 0.042963871 | K8: Utilidad Neta | L8: =B8 -> 1036253 | M8: =C8 -> 1276064 | N8: =D8 -> 1912650 | O8: =C8-B8 -> 239811 | P8: =D8-C8 -> 636586 | Q8: =(C8-B8)/B8 -> 0.23142128 | R8: =(D8-C8)/C8 -> 0.49886683
F11: Año | G11: Margen Bruto | H11: Margen Operativo | I11: Margen Neto
F12: 2023 | G12: =G5/G3 -> 0.58511928 | H12: =G7/G3 -> 0.20379575 | I12: =G8/G3 -> 0.032963871
F13: 2024 | G13: =H5/H3 -> 0.58511928 | H13: =H7/H3 -> 0.28932354 | I13: =H8/H3 -> 0.032963871
F14: 2025 Q2 | G14: =I5/I3 -> 0.60011928 | H14: =I7/I3 -> 0.2920191 | I14: =I8/I3 -> 0.042963871

Sheet base de datos
A1: Métrica | B1: Año | C1: Valor (USD)
A2: Ingresos Totales | B2: 2023 | C2: 31436023
A3: Ingresos Totales | B3: 2024 | C3: 38710988
A4: Ingresos Totales | B4: 2025 | C4: 44517636
A5: Costo de Ventas | B5: 2023 | C5: 13042200
A6: Costo de Ventas | B6: 2024 | C6: 16060443
A7: Costo de Ventas | B7: 2025 | C7: 17801745
A8: Utilidad Bruta | B8: 2023 | C8: 18393823
A9: Utilidad Bruta | B9: 2024 | C9: 22650545
A10: Utilidad Bruta | B10: 2025 | C10: 26715892
A11: EBITDA | B11: 2023 | C11: 11221761
A12: EBITDA | B12: 2024 | C12: 13818715
A13: EBITDA | B13: 2025 | C13: 16559287
... A19: Utilidad Neta | B19: 2025 | C19: 1912650
